Metadata-Version: 2.1
Name: openvalidators
Version: 1.0.4
Summary: Openvalidators is a collection of open source validators for the Bittensor Network.
Home-page: https://github.com/opentensor/validators
Author: bittensor.com
Author-email: 
Maintainer: 
Maintainer-email: 
License: MIT
Keywords: bittensor,validator,ai,machine-learning,deep-learning,blockchain,pytorch,torch,neural-networks,cryptocurrency
Classifier: Intended Audience :: Developers
Classifier: Topic :: Software Development :: Build Tools
Classifier: License :: OSI Approved :: MIT License
Classifier: Programming Language :: Python :: 3 :: Only
Classifier: Programming Language :: Python :: 3.8
Classifier: Programming Language :: Python :: 3.9
Classifier: Programming Language :: Python :: 3.10
Classifier: Topic :: Scientific/Engineering
Classifier: Topic :: Scientific/Engineering :: Mathematics
Classifier: Topic :: Scientific/Engineering :: Artificial Intelligence
Classifier: Topic :: Software Development
Classifier: Topic :: Software Development :: Libraries
Classifier: Topic :: Software Development :: Libraries :: Python Modules
Requires-Python: >=3.8
License-File: LICENSE
Requires-Dist: bittensor (==5.1.0)
Requires-Dist: transformers (==4.20.1)
Requires-Dist: wandb (==0.15.3)
Requires-Dist: datasets (==2.12.0)
Requires-Dist: plotly (==5.14.1)
Requires-Dist: networkx (==3.1)
Requires-Dist: scipy (==1.10.1)
Requires-Dist: pre-commit (==3.3.2)
Requires-Dist: click (==8.1.3)
